mgpus/README.md
mgpus/__about__.py
mgpus/__init__.py
mgpus/main.py
mgpus/requirements.txt
mgpus-0.1.3.dist-info/METADATA
mgpus-0.1.3.dist-info/WHEEL
mgpus-0.1.3.dist-info/entry_points.txt
mgpus-0.1.3.dist-info/licenses/LICENSE
mgpus-0.1.3.dist-info/RECORD
