Metadata-Version: 2.3
Name: mgpus
Version: 0.1.3
Summary: List GPU processes and their memory usage
Project-URL: Documentation, https://github.com/mbodiai/mgpus#readme
Project-URL: Issues, https://github.com/mbodiai/mgpus/issues
Project-URL: Source, https://github.com/mbodiai/mgpus
Author: mbodiai
License-Expression: Apache-2.0
License-File: LICENSE
Classifier: Development Status :: 4 - Beta
Classifier: Programming Language :: Python
Classifier: Programming Language :: Python :: 3.9
Classifier: Programming Language :: Python :: 3.10
Classifier: Programming Language :: Python :: 3.11
Classifier: Programming Language :: Python :: 3.12
Classifier: Programming Language :: Python :: Implementation :: CPython
Classifier: Programming Language :: Python :: Implementation :: PyPy
Requires-Python: >=3.9
Requires-Dist: click
Requires-Dist: psutil
Requires-Dist: pynvml
Requires-Dist: rich
